{
  "daily_report_25_26":
  {
    "project_name": "2025-2026供暖期生产日报",
    "pages":{
      "dashboard":
      {
        "页面名称":"数据看板",
        "数据源":"开发中……",
        "页面描述":"查看整体数据仪表盘"
      },
      "data_show":
      {
        "页面名称":"数据展示页面",
        "数据源":"/app/data/数据结构_全口径展示表.json",
        "页面描述":"浏览固定数据展示表"
      },
      "data_approval":
      {
        "页面名称":"数据审批页面",
        "数据源":"/app/data/数据结构_审批用表.json",
        "页面描述":"处理审批流程进度"
      },
      "data_entry":
      {
        "页面名称":"每日数据填报页面",
        "数据源":"/app/data/数据结构_基本指标表.json",
        "页面描述":"填写并提交日报数据"
      } ,
      "constant_data":
      {
        "页面名称":"常量指标页面",
        "数据源":"/app/data/数据结构_常量指标表.json",
        "页面描述":"维护常量指标数据"
      },      
      "data_analysis":
      {
        "页面名称":"数据分析页面",
        "数据源":"/app/data/数据结构_数据分析表.json",
        "页面描述":"数据自由组合提取"
      },
      "/debug/runtime-eval":
      {
        "页面名称":"运行时表达式求值（调试）",
        "数据源":"configs/字典样例.json",
        "页面描述":"运行时表达式调试工具，仅限技术人员"
      }
    }
  }
}
